sche/__init__.py
sche-1.0a5.data/scripts/sche
sche-1.0a5.dist-info/AUTHORS.rst
sche-1.0a5.dist-info/LICENSE.txt
sche-1.0a5.dist-info/METADATA
sche-1.0a5.dist-info/WHEEL
sche-1.0a5.dist-info/top_level.txt
sche-1.0a5.dist-info/RECORD
