Metadata-Version: 2.1
Name: sche
Version: 1.0a5
Summary: Job scheduling for humans.
Home-page: https://github.com/yifeikong/sche
Author: Yifei Kong
Author-email: kong@yifei.me
License: MIT
Download-URL: https://github.com/yifeikong/sche/tarball/1.0a5
Keywords: schedule,periodic,jobs,scheduling,clockwork,cron,scheduler,job scheduling
Platform: UNKNOWN
Classifier: Intended Audience :: Developers
Classifier: License :: OSI Approved :: MIT License
Classifier: Programming Language :: Python
Classifier: Programming Language :: Python :: 3
Classifier: Programming Language :: Python :: 3.6
Classifier: Programming Language :: Python :: 3.7
Classifier: Programming Language :: Python :: 3.8
Classifier: Natural Language :: English
Requires-Python: >=3.6
